odoo8_addon_crm_rma_location-8.0.1.0.0.99.dev12-nspkg.pth
odoo_addons/crm_rma_location/README.rst
odoo_addons/crm_rma_location/__init__.py
odoo_addons/crm_rma_location/__openerp__.py
odoo_addons/crm_rma_location/i18n/crm_rma_location.pot
odoo_addons/crm_rma_location/i18n/de.po
odoo_addons/crm_rma_location/i18n/es.po
odoo_addons/crm_rma_location/i18n/es_ES.po
odoo_addons/crm_rma_location/i18n/es_MX.po
odoo_addons/crm_rma_location/i18n/es_PA.po
odoo_addons/crm_rma_location/i18n/es_VE.po
odoo_addons/crm_rma_location/i18n/fr.po
odoo_addons/crm_rma_location/i18n/it.po
odoo_addons/crm_rma_location/i18n/pt_BR.po
odoo_addons/crm_rma_location/i18n/sk.po
odoo_addons/crm_rma_location/i18n/sl.po
odoo_addons/crm_rma_location/i18n/tr_TR.po
odoo_addons/crm_rma_location/models/__init__.py
odoo_addons/crm_rma_location/models/stock_warehouse.py
odoo_addons/crm_rma_location/static/description/icon.png
odoo_addons/crm_rma_location/tests/__init__.py
odoo_addons/crm_rma_location/tests/test_location_rma.py
odoo_addons/crm_rma_location/views/stock_warehouse.xml
odoo8_addon_crm_rma_location-8.0.1.0.0.99.dev12.dist-info/METADATA
odoo8_addon_crm_rma_location-8.0.1.0.0.99.dev12.dist-info/WHEEL
odoo8_addon_crm_rma_location-8.0.1.0.0.99.dev12.dist-info/namespace_packages.txt
odoo8_addon_crm_rma_location-8.0.1.0.0.99.dev12.dist-info/top_level.txt
odoo8_addon_crm_rma_location-8.0.1.0.0.99.dev12.dist-info/RECORD
